{"imdb":"tt0182576","links":[{"quality":"480p","link":"http://dl13.ftk.pw/user/shahab/serial/Family Guy/S18/Family.Guy.S18E01.480p.Film2Movie_WS.mkv","season":18,"episode":1},{"quality":"480p","link":"https://dl14.ftk.pw/user/shahab/serial/Family Guy/S18/Family.Guy.S18E05.480p.Film2Movie_li.mkv","season":18,"episode":5},{"quality":"720p","link":"https://dl14.ftk.pw/user/shahab/serial/Family Guy/S18/Family.Guy.S18E05.720p.Film2Movie_li.mkv","season":18,"episode":5},{"quality":"1080p","link":"https://dl14.ftk.pw/user/shahab/serial/Family Guy/S18/Family.Guy.S18E05.1080p.Film2Movie_li.mkv","season":18,"episode":5},{"quality":"720p","link":"https://dl14.ftk.pw/user/shahab/serial/Family Guy/S18/Family.Guy.S18E05.720p.x265.HEVC.Film2Movie_li.mkv","season":18,"episode":5},{"quality":"1080p","link":"https://dl14.ftk.pw/user/shahab/serial/Family Guy/S18/Family.Guy.S18E04.1080p.Film2Movie_li.mkv","season":18,"episode":4},{"quality":"720p","link":"https://dl14.ftk.pw/user/shahab/serial/Family Guy/S18/Family.Guy.S18E06.720p.x265.HEVC.Film2Movie_li.mkv","season":18,"episode":6},{"quality":"480p","link":"https://dl14.ftk.pw/user/shahab/serial/Family Guy/S18/Family.Guy.S18E06.480p.Film2Movie_li.mkv","season":18,"episode":6},{"quality":"720p","link":"https://dl14.ftk.pw/user/shahab/serial/Family Guy/S18/Family.Guy.S18E06.720p.Film2Movie_li.mkv","season":18,"episode":6},{"quality":"720p","link":"https://dl14.ftk.pw/user/shahab/serial/Family Guy/S18/Family.Guy.S18E07.720p.x265.HEVC.Film2Movie_li.mkv","season":18,"episode":7},{"quality":"480p","link":"https://dl14.ftk.pw/user/shahab/serial/Family Guy/S18/Family.Guy.S18E07.480p.Film2Movie_li.mkv","season":18,"episode":7},{"quality":"480p","link":"https://dl14.ftk.pw/user/shahab/serial/Family Guy/S18/Family.Guy.S18E04.480p.Film2Movie_li.mkv","season":18,"episode":4},{"quality":"1080p","link":"https://dl14.ftk.pw/user/shahab/serial/Family Guy/S18/Family.Guy.S18E07.1080p.Film2Movie_li.mkv","season":18,"episode":7},{"quality":"720p","link":"https://dl14.ftk.pw/user/shahab/serial/Family Guy/S18/Family.Guy.S18E04.720p.x265.HEVC.Film2Movie_li.mkv","season":18,"episode":4},{"quality":"720p","link":"https://dl14.ftk.pw/user/shahab/serial/Family Guy/S18/Family.Guy.S18E07.720p.Film2Movie_li.mkv","season":18,"episode":7},{"quality":"720p","link":"https://dl14.ftk.pw/user/shahab/serial/Family Guy/S18/Family.Guy.S18E04.720p.Film2Movie_li.mkv","season":18,"episode":4},{"quality":"1080p","link":"https://dl14.ftk.pw/user/shahab/serial/Family Guy/S18/Family.Guy.S18E08.1080p.Film2Movie_li.mkv","season":18,"episode":8},{"quality":"480p","link":"https://dl14.ftk.pw/user/shahab/serial/Family Guy/S18/Family.Guy.S18E03.480p.Film2Movie_li.mkv","season":18,"episode":3},{"quality":"720p","link":"https://dl14.ftk.pw/user/shahab/serial/Family Guy/S18/Family.Guy.S18E08.720p.Film2Movie_li.mkv","season":18,"episode":8},{"quality":"720p","link":"https://dl14.ftk.pw/user/shahab/serial/Family Guy/S18/Family.Guy.S18E03.720p.Film2Movie_li.mkv","season":18,"episode":3},{"quality":"480p","link":"https://dl14.ftk.pw/user/shahab/serial/Family Guy/S18/Family.Guy.S18E08.480p.Film2Movie_li.mkv","season":18,"episode":8},{"quality":"1080p","link":"https://dl14.ftk.pw/user/shahab/serial/Family Guy/S18/Family.Guy.S18E03.1080p.Film2Movie_li.mkv","season":18,"episode":3},{"quality":"720p","link":"https://dl14.ftk.pw/user/shahab/serial/Family Guy/S18/Family.Guy.S18E08.720p.x265.HEVC.Film2Movie_li.mkv","season":18,"episode":8},{"quality":"720p","link":"https://dl14.ftk.pw/user/shahab/serial/Family Guy/S18/Family.Guy.S18E03.720p.x265.HEVC.Film2Movie_li.mkv","season":18,"episode":3},{"quality":"720p","link":"https://dl14.ftk.pw/user/shahab/serial/Family Guy/S18/Family.Guy.S18E09.720p.Film2Movie_li.mkv","season":18,"episode":9},{"quality":"720p","link":"https://dl14.ftk.pw/user/shahab/serial/Family Guy/S18/Family.Guy.S18E02.720p.x265.HEVC.Film2Movie_li.mkv","season":18,"episode":2},{"quality":"720p","link":"https://dl14.ftk.pw/user/shahab/serial/Family Guy/S18/Family.Guy.S18E09.720p.x265.HEVC.Film2Movie_li.mkv","season":18,"episode":9},{"quality":"720p","link":"https://dl14.ftk.pw/user/shahab/serial/Family Guy/S18/Family.Guy.S18E02.720p.Film2Movie_li.mkv","season":18,"episode":2},{"quality":"480p","link":"https://dl14.ftk.pw/user/shahab/serial/Family Guy/S18/Family.Guy.S18E09.480p.Film2Movie_li.mkv","season":18,"episode":9},{"quality":"1080p","link":"https://dl14.ftk.pw/user/shahab/serial/Family Guy/S18/Family.Guy.S18E02.1080p.Film2Movie_li.mkv","season":18,"episode":2},{"quality":"1080p","link":"https://dl14.ftk.pw/user/shahab/serial/Family Guy/S18/Family.Guy.S18E09.1080p.Film2Movie_li.mkv","season":18,"episode":9},{"quality":"480p","link":"https://dl14.ftk.pw/user/shahab/serial/Family Guy/S18/Family.Guy.S18E02.480p.Film2Movie_li.mkv","season":18,"episode":2},{"quality":"720p","link":"https://dl14.ftk.pw/user/shahab/serial/Family Guy/S18/Family.Guy.S18E10.720p.Film2Movie_li.mkv","season":18,"episode":10},{"quality":"720p","link":"http://dl13.ftk.pw/user/shahab/serial/Family Guy/S18/Family.Guy.S18E01.720p.x265.HEVC.Film2Movie_WS.mkv","season":18,"episode":1},{"quality":"480p","link":"https://dl14.ftk.pw/user/shahab/serial/Family Guy/S18/Family.Guy.S18E10.480p.Film2Movie_li.mkv","season":18,"episode":10},{"quality":"720p","link":"http://dl13.ftk.pw/user/shahab/serial/Family Guy/S18/Family.Guy.S18E01.720p.Film2Movie_WS.mkv","season":18,"episode":1},{"quality":"1080p","link":"https://dl14.ftk.pw/user/shahab/serial/Family Guy/S18/Family.Guy.S18E10.1080p.Film2Movie_li.mkv","season":18,"episode":10},{"quality":"1080p","link":"http://dl13.ftk.pw/user/shahab/serial/Family Guy/S18/Family.Guy.S18E01.1080p.Film2Movie_WS.mkv","season":18,"episode":1},{"quality":"720p","link":"https://dl14.ftk.pw/user/shahab/serial/Family Guy/S18/Family.Guy.S18E10.720p.x265.HEVC.Film2Movie_li.mkv","season":18,"episode":10},{"quality":"1080p","link":"https://dl14.ftk.pw/user/shahab/serial/Family Guy/S18/Family.Guy.S18E06.1080p.Film2Movie_li.mkv","season":18,"episode":6}],"trailers":[{"quality":"360p","link":"http://dl13.ftk.pw/user/shahab/serial/Family Guy/S18/Family.Guy.S18.360p.Trailer.Film2Movie_WS.mp4","type":"trailer","season":18},{"quality":"720p","link":"http://dl13.ftk.pw/user/shahab/serial/Family Guy/S18/Family.Guy.S18.720p.Trailer.Film2Movie_WS.mp4","type":"trailer","season":18}],"Info":{"Title":"Family Guy","Year":"1999–","Rated":"TV-14","Released":"31 Jan 1999","Runtime":"22 min","Genre":"Animation, Comedy","Director":"N/A","Writer":"Seth MacFarlane, David Zuckerman","Actors":"Seth MacFarlane, Alex Borstein, Seth Green, Mila Kunis","Plot":"In a wacky Rhode Island town, a dysfunctional family strive to cope with everyday life as they are thrown from one crazy scenario to another.","Language":"English, Portuguese","Country":"USA","Awards":"Won 9 Primetime Emmys. Another 27 wins & 97 nominations.","Poster":"https://m.media-amazon.com/images/M/MV5BODEwZjEzMjAtNjQxMy00Yjc4LWFlMDAtYjhjZTAxNDU3OTg3XkEyXkFqcGdeQXVyOTM2NTM4MjA@._V1_SX300.jpg","Ratings":[{"Source":"Internet Movie Database","Value":"8.1/10"}],"Metascore":"N/A","imdbRating":"8.1","imdbVotes":"290,116","imdbID":"tt0182576","Type":"series","totalSeasons":"18","Response":"True"}}