{"imdb":"tt1553656","links":[{"quality":"480p","link":"http://dl.ftk.pw/serial/Under%20The%20Dome/S01/Under.The.Dome.S01E01.480p.Film2Movie_ORG.mkv","season":1,"episode":1},{"quality":"720p","link":"http://dl.ftk.pw/serial/Under%20The%20Dome/S03/Under.The.Dome.S03E01-E02.720p.x265.HEVC.Film2Movie_ORG.mkv"},{"quality":"480p","link":"http://dl.ftk.pw/serial/Under%20The%20Dome/S01/Under.The.Dome.S01E02.480p.Film2Movie_ORG.mkv","season":1,"episode":2},{"quality":"480p","link":"http://dl.ftk.pw/serial/Under%20The%20Dome/S01/Under.The.Dome.S01E13.480p.Film2Movie_ORG.mkv","season":1,"episode":13},{"quality":"480p","link":"http://dl.ftk.pw/serial/Under%20The%20Dome/S01/Under.The.Dome.S01E06.480p.Film2Movie_ORG.mkv","season":1,"episode":6},{"quality":"720p","link":"http://dl.ftk.pw/serial/Under%20The%20Dome/S03/Under.The.Dome.S03E01-E02.720p.Film2Movie_ORG.mkv"},{"quality":"480p","link":"http://dl.ftk.pw/serial/Under%20The%20Dome/S01/Under.The.Dome.S01E12.480p.Film2Movie_ORG.mkv","season":1,"episode":12},{"quality":"480p","link":"http://dl.ftk.pw/serial/Under%20The%20Dome/S01/Under.The.Dome.S01E03.480p.Film2Movie_ORG.mkv","season":1,"episode":3},{"quality":"480p","link":"http://dl.ftk.pw/serial/Under%20The%20Dome/S01/Under.The.Dome.S01E09.480p.Film2Movie_ORG.mkv","season":1,"episode":9},{"quality":"480p","link":"http://dl.ftk.pw/serial/Under%20The%20Dome/S01/Under.The.Dome.S01E05.480p.Film2Movie_ORG.mkv","season":1,"episode":5},{"quality":"480p","link":"http://dl.ftk.pw/serial/Under%20The%20Dome/S01/Under.The.Dome.S01E10.480p.Film2Movie_ORG.mkv","season":1,"episode":10},{"quality":"480p","link":"http://dl.ftk.pw/serial/Under%20The%20Dome/S03/Under.The.Dome.S03E01-E02.480p.Film2Movie_ORG.mkv"},{"quality":"480p","link":"http://dl.ftk.pw/serial/Under%20The%20Dome/S01/Under.The.Dome.S01E11.480p.Film2Movie_ORG.mkv","season":1,"episode":11},{"quality":"480p","link":"http://dl.ftk.pw/serial/Under%20The%20Dome/S01/Under.The.Dome.S01E08.480p.Film2Movie_ORG.mkv","season":1,"episode":8},{"quality":"480p","link":"http://dl.ftk.pw/serial/Under%20The%20Dome/S01/Under.The.Dome.S01E07.480p.Film2Movie_ORG.mkv","season":1,"episode":7},{"quality":"480p","link":"http://dl.ftk.pw/serial/Under%20The%20Dome/S01/Under.The.Dome.S01E04.480p.Film2Movie_ORG.mkv","season":1,"episode":4},{"quality":"480p","link":"http://dl.ftk.pw/serial/Under%20The%20Dome/S02/Under.The.Dome.S02E10.480p.Film2Movie_ORG.mkv","season":2,"episode":10},{"quality":"480p","link":"http://dl.ftk.pw/serial/Under%20The%20Dome/S02/Under.The.Dome.S02E12.480p.Film2Movie_ORG.mkv","season":2,"episode":12},{"quality":"480p","link":"http://dl.ftk.pw/serial/Under%20The%20Dome/S02/Under.The.Dome.S02E05.480p.Film2Movie_ORG.mkv","season":2,"episode":5},{"quality":"480p","link":"http://dl.ftk.pw/serial/Under%20The%20Dome/S02/Under.The.Dome.S02E04.480p.Film2Movie_ORG.mkv","season":2,"episode":4},{"quality":"480p","link":"http://dl.ftk.pw/serial/Under%20The%20Dome/S02/Under.The.Dome.S02E09.480p.Film2Movie_ORG.mkv","season":2,"episode":9},{"quality":"480p","link":"http://dl.ftk.pw/serial/Under%20The%20Dome/S02/Under.The.Dome.S02E03.480p.Film2Movie_ORG.mkv","season":2,"episode":3},{"quality":"480p","link":"http://dl.ftk.pw/serial/Under%20The%20Dome/S02/Under.The.Dome.S02E13.480p.Film2Movie_ORG.mkv","season":2,"episode":13},{"quality":"480p","link":"http://dl.ftk.pw/serial/Under%20The%20Dome/S02/Under.The.Dome.S02E08.480p.Film2Movie_ORG.mkv","season":2,"episode":8},{"quality":"480p","link":"http://dl.ftk.pw/serial/Under%20The%20Dome/S02/Under.The.Dome.S02E02.480p.Film2Movie_ORG.mkv","season":2,"episode":2},{"quality":"480p","link":"http://dl.ftk.pw/serial/Under%20The%20Dome/S02/Under.The.Dome.S02E11.480p.Film2Movie_ORG.mkv","season":2,"episode":11},{"quality":"480p","link":"http://dl.ftk.pw/serial/Under%20The%20Dome/S02/Under.The.Dome.S02E01.480p.Film2Movie_ORG.mkv","season":2,"episode":1},{"quality":"480p","link":"http://dl.ftk.pw/serial/Under%20The%20Dome/S02/Under.The.Dome.S02E06.480p.Film2Movie_ORG.mkv","season":2,"episode":6},{"quality":"480p","link":"http://dl.ftk.pw/serial/Under%20The%20Dome/S02/Under.The.Dome.S02E07.480p.Film2Movie_ORG.mkv","season":2,"episode":7},{"quality":"480p","link":"http://dl.ftk.pw/serial/Under%20The%20Dome/S03/Under.The.Dome.S03E07.480p.Film2Movie_ORG.mkv","season":3,"episode":7},{"quality":"480p","link":"http://dl.ftk.pw/serial/Under%20The%20Dome/S03/Under.The.Dome.S03E05.480p.Film2Movie_ORG.mkv","season":3,"episode":5},{"quality":"720p","link":"http://dl.ftk.pw/serial/Under%20The%20Dome/S03/Under.The.Dome.S03E05.720p.Film2Movie_ORG.mkv","season":3,"episode":5},{"quality":"720p","link":"http://dl.ftk.pw/serial/Under%20The%20Dome/S03/Under.The.Dome.S03E10.720p.Film2Movie_ORG.mkv","season":3,"episode":10},{"quality":"480p","link":"http://dl.ftk.pw/serial/Under%20The%20Dome/S03/Under.The.Dome.S03E09.480p.Film2Movie_ORG.mkv","season":3,"episode":9},{"quality":"480p","link":"http://dl.ftk.pw/serial/Under%20The%20Dome/S03/Under.The.Dome.S03E10.480p.Film2Movie_ORG.mkv","season":3,"episode":10},{"quality":"720p","link":"http://dl.ftk.pw/serial/Under%20The%20Dome/S03/Under.The.Dome.S03E11.720p.Film2Movie_INFO.mkv","season":3,"episode":11},{"quality":"480p","link":"http://dl.ftk.pw/serial/Under%20The%20Dome/S03/Under.The.Dome.S03E04.480p.Film2Movie_ORG.mkv","season":3,"episode":4},{"quality":"720p","link":"http://dl.ftk.pw/serial/Under%20The%20Dome/S03/Under.The.Dome.S03E04.720p.x265.HEVC.Film2Movie_ORG.mkv","season":3,"episode":4},{"quality":"720p","link":"http://dl.ftk.pw/serial/Under%20The%20Dome/S03/Under.The.Dome.S03E11.720p.x265.HEVC.Film2Movie_INFO.mkv","season":3,"episode":11},{"quality":"720p","link":"http://dl.ftk.pw/serial/Under%20The%20Dome/S03/Under.The.Dome.S03E05.720p.x265.HEVC.Film2Movie_ORG.mkv","season":3,"episode":5},{"quality":"480p","link":"http://dl.ftk.pw/serial/Under%20The%20Dome/S03/Under.The.Dome.S03E11.480p.Film2Movie_INFO.mkv","season":3,"episode":11},{"quality":"480p","link":"http://dl.ftk.pw/serial/Under%20The%20Dome/S03/Under.The.Dome.S03E06.480p.Film2Movie_ORG.mkv","season":3,"episode":6},{"quality":"720p","link":"http://dl.ftk.pw/serial/Under%20The%20Dome/S03/Under.The.Dome.S03E12.720p.Film2Movie_INFO.mkv","season":3,"episode":12},{"quality":"720p","link":"http://dl.ftk.pw/serial/Under%20The%20Dome/S03/Under.The.Dome.S03E09.720p.Film2Movie_ORG.mkv","season":3,"episode":9},{"quality":"720p","link":"http://dl.ftk.pw/serial/Under%20The%20Dome/S03/Under.The.Dome.S03E04.720p.Film2Movie_ORG.mkv","season":3,"episode":4},{"quality":"720p","link":"http://dl.ftk.pw/serial/Under%20The%20Dome/S03/Under.The.Dome.S03E09.720p.x265.HEVC.Film2Movie_ORG.mkv","season":3,"episode":9},{"quality":"480p","link":"http://dl.ftk.pw/serial/Under%20The%20Dome/S03/Under.The.Dome.S03E03.480p.Film2Movie_ORG.mkv","season":3,"episode":3},{"quality":"720p","link":"http://dl.ftk.pw/serial/Under%20The%20Dome/S03/Under.The.Dome.S03E08.720p.Film2Movie_ORG.mkv","season":3,"episode":8},{"quality":"480p","link":"http://dl.ftk.pw/serial/Under%20The%20Dome/S03/Under.The.Dome.S03E12.480p.Film2Movie_INFO.mkv","season":3,"episode":12},{"quality":"720p","link":"http://dl.ftk.pw/serial/Under%20The%20Dome/S03/Under.The.Dome.S03E08.720p.x265.HEVC.Film2Movie_ORG.mkv","season":3,"episode":8},{"quality":"720p","link":"http://dl.ftk.pw/serial/Under%20The%20Dome/S03/Under.The.Dome.S03E12.720p.x265.HEVC.Film2Movie_INFO.mkv","season":3,"episode":12},{"quality":"720p","link":"http://dl.ftk.pw/serial/Under%20The%20Dome/S03/Under.The.Dome.S03E06.720p.x265.HEVC.Film2Movie_ORG.mkv","season":3,"episode":6},{"quality":"720p","link":"http://dl.ftk.pw/serial/Under%20The%20Dome/S03/Under.The.Dome.S03E13.720p.x265.HEVC.Film2Movie_INFO.mkv","season":3,"episode":13},{"quality":"720p","link":"http://dl.ftk.pw/serial/Under%20The%20Dome/S03/Under.The.Dome.S03E06.720p.Film2Movie_ORG.mkv","season":3,"episode":6},{"quality":"720p","link":"http://dl.ftk.pw/serial/Under%20The%20Dome/S03/Under.The.Dome.S03E03.720p.Film2Movie_ORG.mkv","season":3,"episode":3},{"quality":"480p","link":"http://dl.ftk.pw/serial/Under%20The%20Dome/S03/Under.The.Dome.S03E08.480p.Film2Movie_ORG.mkv","season":3,"episode":8},{"quality":"720p","link":"http://dl.ftk.pw/serial/Under%20The%20Dome/S03/Under.The.Dome.S03E13.720p.Film2Movie_INFO.mkv","season":3,"episode":13},{"quality":"720p","link":"http://dl.ftk.pw/serial/Under%20The%20Dome/S03/Under.The.Dome.S03E07.720p.Film2Movie_ORG.mkv","season":3,"episode":7},{"quality":"720p","link":"http://dl.ftk.pw/serial/Under%20The%20Dome/S03/Under.The.Dome.S03E03.720p.x265.HEVC.Film2Movie_ORG.mkv","season":3,"episode":3},{"quality":"720p","link":"http://dl.ftk.pw/serial/Under%20The%20Dome/S03/Under.The.Dome.S03E07.720p.x265.HEVC.Film2Movie_ORG.mkv","season":3,"episode":7},{"quality":"480p","link":"http://dl.ftk.pw/serial/Under%20The%20Dome/S03/Under.The.Dome.S03E13.480p.Film2Movie_INFO.mkv","season":3,"episode":13},{"quality":"720p","link":"http://dl.ftk.pw/serial/Under%20The%20Dome/S03/Under.The.Dome.S03E10.720p.x265.HEVC.Film2Movie_ORG.mkv","season":3,"episode":10}],"trailers":[],"Info":{}}