{"imdb":"tt2299206","links":[],"trailers":[],"Info":{"Title":"Blood Glacier","Year":"2013","Rated":"Not Rated","Released":"27 Sep 2013","Runtime":"98 min","Genre":"Horror, Mystery, Sci-Fi, Thriller","Director":"Marvin Kren","Writer":"Benjamin Hessler (screenplay), Marvin Kren (screenplay contributor), Claudia Kolland (dramatisation)","Actors":"Gerhard Liebmann, Edita Malovcic, Santos, Hille Beseler","Plot":"Scientists working in the Austrian Alps discover that a glacier is leaking a liquid that appears to be affecting local wildlife.","Language":"German","Country":"Austria","Awards":"4 wins & 2 nominations.","Poster":"https://m.media-amazon.com/images/M/MV5BMzdjYTE3NzktZjdlZS00NTU4LWFlNmItOGJiZGE4OTk3YzAxXkEyXkFqcGdeQXVyODU2MDg1NzU@._V1_SX300.jpg","Ratings":[{"Source":"Internet Movie Database","Value":"5.4/10"},{"Source":"Rotten Tomatoes","Value":"43%"},{"Source":"Metacritic","Value":"45/100"}],"Metascore":"45","imdbRating":"5.4","imdbVotes":"3,223","imdbID":"tt2299206","Type":"movie","DVD":"26 Aug 2014","BoxOffice":"N/A","Production":"Allegro Film","Website":"N/A","Response":"True"}}