{"imdb":"tt2635006","links":[],"trailers":[],"Info":{"Title":"The Retrieval","Year":"2013","Rated":"R","Released":"02 Apr 2014","Runtime":"92 min","Genre":"Adventure, Drama, Western","Director":"Chris Eska","Writer":"Chris Eska","Actors":"Ashton Sanders, Tishuan Scott, Keston John, Bill Oberst Jr.","Plot":"On the outskirts of the U.S. Civil War, a boy is sent north by his bounty hunter gang to retrieve a wanted man.","Language":"English","Country":"USA","Awards":"9 wins & 3 nominations.","Poster":"https://m.media-amazon.com/images/M/MV5BNjU3Mzk3MjU4Nl5BMl5BanBnXkFtZTgwNDQzOTczMTE@._V1_SX300.jpg","Ratings":[{"Source":"Internet Movie Database","Value":"6.6/10"},{"Source":"Rotten Tomatoes","Value":"93%"},{"Source":"Metacritic","Value":"75/100"}],"Metascore":"75","imdbRating":"6.6","imdbVotes":"2,352","imdbID":"tt2635006","Type":"movie","DVD":"03 Feb 2015","BoxOffice":"$50,257","Production":"Variance Films","Website":"N/A","Response":"True"}}