{"imdb":"tt3446852","links":[],"trailers":[],"Info":{"Title":"Bodybuilder","Year":"2014","Rated":"N/A","Released":"01 Oct 2014","Runtime":"100 min","Genre":"Drama","Director":"Roschdy Zem","Writer":"Roschdy Zem (screenplay), Julie Peyr (screenplay), Bryan Friedman (novel)","Actors":"Vincent Rottiers, Yolin François Gauvin, Marina Foïs, Nicolas Duvauchelle","Plot":"Twenty year old Antoine has made enemies of a gang of young thugs, to whom he owes money. Fed up with his scams and petty crimes, his mother and older brother decide to send Antoine to his ...","Language":"French","Country":"France","Awards":"N/A","Poster":"https://m.media-amazon.com/images/M/MV5BZmYxYTMwODEtNmE2ZC00MTJjLWE3NzktNzkxNmVkOTM2YzMwXkEyXkFqcGdeQXVyNjUzNjY0NTE@._V1_SX300.jpg","Ratings":[{"Source":"Internet Movie Database","Value":"6.1/10"}],"Metascore":"N/A","imdbRating":"6.1","imdbVotes":"559","imdbID":"tt3446852","Type":"movie","DVD":"N/A","BoxOffice":"N/A","Production":"Mars Distribution","Website":"N/A","Response":"True"}}