{"imdb":"tt7555774","links":[{"quality":"480p","link":"http://dl8.ftk.pw/film/At.War.2018.480p.BluRay.Film2Movie_WS.mkv"},{"quality":"720p","link":"http://dl8.ftk.pw/film/At.War.2018.720p.BluRay.Film2Movie_WS.mkv"},{"quality":"720p","link":"http://dl8.ftk.pw/film/At.War.2018.720p.BluRay.x265.HEVC.Film2Movie_WS.mkv"},{"quality":"1080p","link":"http://dl8.ftk.pw/film/At.War.2018.1080p.BluRay.Film2Movie_WS.mkv"}],"trailers":[{"quality":"360p","link":"http://dl8.ftk.pw/trailer/At.War.2018.360p.Trailer.Film2Movie_WS.mp4","type":"trailer"},{"quality":"720p","link":"http://dl8.ftk.pw/trailer/At.War.2018.720p.Trailer.Film2Movie_WS.mp4","type":"trailer"}],"Info":{}}